postgresqlite/__init__.py
postgresqlite/__main__.py
postgresqlite-0.4.8.dist-info/METADATA
postgresqlite-0.4.8.dist-info/WHEEL
postgresqlite-0.4.8.dist-info/entry_points.txt
postgresqlite-0.4.8.dist-info/RECORD
