Metadata-Version: 2.1
Name: postgresqlite
Version: 0.4.8
Summary: Python package that gives you the power of a PostgreSQL server, with the convenience of the sqlite3 package.
Home-page: https://github.com/vanviegen/postgresqlite
Author: Frank van Viegen
Author-email: pp@vanviegen.net
Requires-Python: >=3.7,<4.0
Classifier: Development Status :: 4 - Beta
Classifier: License :: OSI Approved :: BSD License
Classifier: Operating System :: POSIX :: Linux
Classifier: Programming Language :: Python :: 3
Classifier: Programming Language :: Python :: 3.7
Classifier: Programming Language :: Python :: 3.8
Classifier: Programming Language :: Python :: 3.9
Classifier: Programming Language :: Python :: 3.10
Classifier: Programming Language :: Python :: 3.11
Classifier: Programming Language :: Python :: 3.12
Classifier: Topic :: Database
Requires-Dist: pg8000 (>=1.24.1,<2.0.0)
Project-URL: Documentation, https://github.com/vanviegen/postgresqlite/blob/master/README.md#Documentation
Project-URL: Repository, https://github.com/vanviegen/postgresqlite
